mcp_codebase_insight/__init__.py
mcp_codebase_insight/__main__.py
mcp_codebase_insight/asgi.py
mcp_codebase_insight/models.py
mcp_codebase_insight/server.py
mcp_codebase_insight/server_test_isolation.py
mcp_codebase_insight/version.py
mcp_codebase_insight/core/__init__.py
mcp_codebase_insight/core/adr.py
mcp_codebase_insight/core/cache.py
mcp_codebase_insight/core/config.py
mcp_codebase_insight/core/debug.py
mcp_codebase_insight/core/di.py
mcp_codebase_insight/core/documentation.py
mcp_codebase_insight/core/embeddings.py
mcp_codebase_insight/core/errors.py
mcp_codebase_insight/core/health.py
mcp_codebase_insight/core/knowledge.py
mcp_codebase_insight/core/metrics.py
mcp_codebase_insight/core/prompts.py
mcp_codebase_insight/core/state.py
mcp_codebase_insight/core/task_tracker.py
mcp_codebase_insight/core/tasks.py
mcp_codebase_insight/core/vector_store.py
mcp_codebase_insight/utils/__init__.py
mcp_codebase_insight/utils/logger.py
mcp_codebase_insight-0.2.2.dist-info/METADATA
mcp_codebase_insight-0.2.2.dist-info/WHEEL
mcp_codebase_insight-0.2.2.dist-info/entry_points.txt
mcp_codebase_insight-0.2.2.dist-info/top_level.txt
mcp_codebase_insight-0.2.2.dist-info/RECORD
