Metadata-Version: 2.4
Name: mcp-codebase-insight
Version: 0.2.2
Summary: MCP Codebase Insight Server
Home-page: https://github.com/modelcontextprotocol/mcp-codebase-insight
Author: Tosin Akinosho
Author-email: info@modelcontextprotocol.org
License: MIT
Project-URL: Homepage, https://github.com/tosin2013/mcp-codebase-insight
Project-URL: Documentation, https://github.com/tosin2013/mcp-codebase-insight/docs
Project-URL: Repository, https://github.com/tosin2013/mcp-codebase-insight.git
Project-URL: Issues, https://github.com/tosin2013/mcp-codebase-insight/issues
Classifier: Development Status :: 3 - Alpha
Classifier: Intended Audience :: Developers
Classifier: License :: OSI Approved :: MIT License
Classifier: Programming Language :: Python :: 3
Classifier: Programming Language :: Python :: 3.10
Classifier: Programming Language :: Python :: 3.11
Classifier: Topic :: Software Development :: Libraries :: Python Modules
Requires-Python: >=3.9
Requires-Dist: fastapi>=0.103.2
Requires-Dist: uvicorn>=0.23.2
Requires-Dist: pydantic>=2.4.2
Requires-Dist: starlette<0.28.0,>=0.27.0
Requires-Dist: asyncio>=3.4.3
Requires-Dist: aiohttp>=3.9.0
Requires-Dist: qdrant-client>=1.13.3
Requires-Dist: sentence-transformers>=2.2.2
Requires-Dist: torch>=2.0.0
Requires-Dist: transformers>=4.34.0
Requires-Dist: python-frontmatter>=1.0.0
Requires-Dist: markdown>=3.4.4
Requires-Dist: PyYAML>=6.0.1
Requires-Dist: structlog>=23.1.0
Requires-Dist: psutil>=5.9.5
Requires-Dist: python-dotenv>=1.0.0
Requires-Dist: requests>=2.31.0
Requires-Dist: beautifulsoup4>=4.12.0
Requires-Dist: scipy>=1.11.0
Requires-Dist: python-slugify>=8.0.0
Requires-Dist: slugify>=0.0.1
Requires-Dist: numpy>=1.24.0
Provides-Extra: test
Requires-Dist: pytest>=7.4.2; extra == "test"
Requires-Dist: pytest-asyncio>=0.21.1; extra == "test"
Requires-Dist: pytest-cov>=4.1.0; extra == "test"
Requires-Dist: httpx>=0.25.0; extra == "test"
Provides-Extra: dev
Requires-Dist: black>=23.9.1; extra == "dev"
Requires-Dist: isort>=5.12.0; extra == "dev"
Requires-Dist: mypy>=1.5.1; extra == "dev"
Requires-Dist: flake8>=6.1.0; extra == "dev"
Requires-Dist: bump2version>=1.0.1; extra == "dev"
Requires-Dist: pre-commit>=3.5.0; extra == "dev"
Requires-Dist: pdoc>=14.1.0; extra == "dev"
Dynamic: author-email
Dynamic: home-page
Dynamic: requires-python
